{"_path":"/deployments/folder2/dokku","_draft":false,"_partial":false,"_locale":"en","_empty":false,"title":"Dokku","description":"How to deploy a Nuxt application on Dokku?","excerpt":{"type":"root","children":[{"type":"element","tag":"h1","props":{"id":"deploy-nuxt-on-dokku"},"children":[{"type":"text","value":"Deploy Nuxt on Dokku"}]},{"type":"element","tag":"p","props":{},"children":[{"type":"text","value":"How to deploy a Nuxt application on Dokku?"}]},{"type":"element","tag":"hr","props":{},"children":[]},{"type":"element","tag":"p","props":{},"children":[{"type":"text","value":"We recommend to read "},{"type":"element","tag":"a","props":{"href":"http://dokku.viewdocs.io/dokku/getting-started/installation/","rel":["nofollow"]},"children":[{"type":"text","value":"Dokku documentation for the setup"}]},{"type":"text","value":" and "},{"type":"element","tag":"a","props":{"href":"http://jakeklassen.com/post/deploying-a-node-app-on-digital-ocean-using-dokku/","rel":["nofollow"]},"children":[{"type":"text","value":"Deploying a Node.js Application on Digital Ocean using Dokku"}]},{"type":"text","value":"."}]},{"type":"element","tag":"p","props":{},"children":[{"type":"text","value":"For the example, we will call our Nuxt application "},{"type":"element","tag":"code-inline","props":{},"children":[{"type":"text","value":"my-nuxt-app"}]},{"type":"text","value":"."}]},{"type":"element","tag":"p","props":{},"children":[{"type":"text","value":"We need to tell Dokku to install the "},{"type":"element","tag":"code-inline","props":{},"children":[{"type":"text","value":"devDependencies"}]},{"type":"text","value":" of the project (to be able to launch "},{"type":"element","tag":"code-inline","props":{},"children":[{"type":"text","value":"npm run build"}]},{"type":"text","value":"):"}]},{"type":"element","tag":"code","props":{"code":"// on Dokku Server\r\ndokku config:set my-nuxt-app NPM_CONFIG_PRODUCTION=false YARN_PRODUCTION=false\n","language":"bash"},"children":[{"type":"element","tag":"pre","props":{},"children":[{"type":"element","tag":"code","props":{"__ignoreMap":""},"children":[{"type":"text","value":"// on Dokku Server\r\ndokku config:set my-nuxt-app NPM_CONFIG_PRODUCTION=false YARN_PRODUCTION=false\n"}]}]}]},{"type":"element","tag":"p","props":{},"children":[{"type":"text","value":"Also, we want our application to listen on the host "},{"type":"element","tag":"code-inline","props":{},"children":[{"type":"text","value":"0.0.0.0"}]},{"type":"text","value":" and run in production mode:"}]},{"type":"element","tag":"code","props":{"code":"// on Dokku Server\r\ndokku config:set my-nuxt-app HOST=0.0.0.0 NODE_ENV=production\n","language":"bash"},"children":[{"type":"element","tag":"pre","props":{},"children":[{"type":"element","tag":"code","props":{"__ignoreMap":""},"children":[{"type":"text","value":"// on Dokku Server\r\ndokku config:set my-nuxt-app HOST=0.0.0.0 NODE_ENV=production\n"}]}]}]},{"type":"element","tag":"p","props":{},"children":[{"type":"text","value":"You should see these 3 lines when you type "},{"type":"element","tag":"code-inline","props":{},"children":[{"type":"text","value":"dokku config my-nuxt-app"}]}]},{"type":"element","tag":"p","props":{},"children":[{"type":"element","tag":"img","props":{"alt":"nuxt config vars Dokku","src":"https://i.imgur.com/9FNsaoQ.png"},"children":[]}]},{"type":"element","tag":"p","props":{},"children":[{"type":"text","value":"Then, we tell Dokku to launch "},{"type":"element","tag":"code-inline","props":{},"children":[{"type":"text","value":"npm run build"}]},{"type":"text","value":" via the "},{"type":"element","tag":"code-inline","props":{},"children":[{"type":"text","value":"scripts.dokku.predeploy"}]},{"type":"text","value":" script in our project "},{"type":"element","tag":"code-inline","props":{},"children":[{"type":"text","value":"app.json"}]},{"type":"text","value":":"}]},{"type":"element","tag":"p","props":{},"children":[{"type":"element","tag":"code-inline","props":{},"children":[{"type":"text","value":"create a file name app.json in our project root folder"}]}]},{"type":"element","tag":"code","props":{"code":"{\r\n  \"scripts\": {\r\n    \"dokku\": {\r\n      \"predeploy\": \"npm run build\"\r\n    }\r\n  }\r\n}\n","language":"js"},"children":[{"type":"element","tag":"pre","props":{},"children":[{"type":"element","tag":"code","props":{"__ignoreMap":""},"children":[{"type":"text","value":"{\r\n  \"scripts\": {\r\n    \"dokku\": {\r\n      \"predeploy\": \"npm run build\"\r\n    }\r\n  }\r\n}\n"}]}]}]},{"type":"element","tag":"p","props":{},"children":[{"type":"text","value":"To launch the application we run "},{"type":"element","tag":"code-inline","props":{},"children":[{"type":"text","value":"npm run start"}]},{"type":"text","value":" using the "},{"type":"element","tag":"a","props":{"href":"http://dokku.viewdocs.io/dokku/deployment/methods/dockerfiles/#procfiles-and-multiple-processes","rel":["nofollow"]},"children":[{"type":"text","value":"Procfile"}]},{"type":"text","value":":"}]},{"type":"element","tag":"code","props":{"code":"web: npm run start\n"},"children":[{"type":"element","tag":"pre","props":{},"children":[{"type":"element","tag":"code","props":{"__ignoreMap":""},"children":[{"type":"text","value":"web: npm run start\n"}]}]}]},{"type":"element","tag":"p","props":{},"children":[{"type":"text","value":"Finally, we can push our app on Dokku with:"}]},{"type":"element","tag":"code","props":{"code":"// commit your change before push.\r\ngit remote add dokku dokku@yourServer:my-nuxt-app\r\ngit push dokku master\n","language":"bash"},"children":[{"type":"element","tag":"pre","props":{},"children":[{"type":"element","tag":"code","props":{"__ignoreMap":""},"children":[{"type":"text","value":"// commit your change before push.\r\ngit remote add dokku dokku@yourServer:my-nuxt-app\r\ngit push dokku master\n"}]}]}]},{"type":"element","tag":"p","props":{},"children":[{"type":"text","value":"Voilà! Our Nuxt application is now hosted on Dokku!"}]}]},"template":"guide","target":"Server","category":"deployment","logo":{"light":"/img/companies/square/light/dokku.png","dark":"/img/companies/square/dark/dokku.png"},"body":{"type":"root","children":[{"type":"element","tag":"h1","props":{"id":"deploy-nuxt-on-dokku"},"children":[{"type":"text","value":"Deploy Nuxt on Dokku"}]},{"type":"element","tag":"p","props":{},"children":[{"type":"text","value":"How to deploy a Nuxt application on Dokku?"}]},{"type":"element","tag":"hr","props":{},"children":[]},{"type":"element","tag":"p","props":{},"children":[{"type":"text","value":"We recommend to read "},{"type":"element","tag":"a","props":{"href":"http://dokku.viewdocs.io/dokku/getting-started/installation/","rel":["nofollow"]},"children":[{"type":"text","value":"Dokku documentation for the setup"}]},{"type":"text","value":" and "},{"type":"element","tag":"a","props":{"href":"http://jakeklassen.com/post/deploying-a-node-app-on-digital-ocean-using-dokku/","rel":["nofollow"]},"children":[{"type":"text","value":"Deploying a Node.js Application on Digital Ocean using Dokku"}]},{"type":"text","value":"."}]},{"type":"element","tag":"p","props":{},"children":[{"type":"text","value":"For the example, we will call our Nuxt application "},{"type":"element","tag":"code-inline","props":{},"children":[{"type":"text","value":"my-nuxt-app"}]},{"type":"text","value":"."}]},{"type":"element","tag":"p","props":{},"children":[{"type":"text","value":"We need to tell Dokku to install the "},{"type":"element","tag":"code-inline","props":{},"children":[{"type":"text","value":"devDependencies"}]},{"type":"text","value":" of the project (to be able to launch "},{"type":"element","tag":"code-inline","props":{},"children":[{"type":"text","value":"npm run build"}]},{"type":"text","value":"):"}]},{"type":"element","tag":"code","props":{"code":"// on Dokku Server\r\ndokku config:set my-nuxt-app NPM_CONFIG_PRODUCTION=false YARN_PRODUCTION=false\n","language":"bash"},"children":[{"type":"element","tag":"pre","props":{},"children":[{"type":"element","tag":"code","props":{"__ignoreMap":""},"children":[{"type":"element","tag":"span","props":{"class":"line"},"children":[{"type":"element","tag":"span","props":{"class":"ct-eb4c6d"},"children":[{"type":"text","value":"// on Dokku Server"}]}]},{"type":"element","tag":"span","props":{"class":"line"},"children":[{"type":"element","tag":"span","props":{"class":"ct-eb4c6d"},"children":[{"type":"text","value":"dokku config:set my-nuxt-app NPM_CONFIG_PRODUCTION=false YARN_PRODUCTION=false"}]}]}]}]}]},{"type":"element","tag":"p","props":{},"children":[{"type":"text","value":"Also, we want our application to listen on the host "},{"type":"element","tag":"code-inline","props":{},"children":[{"type":"text","value":"0.0.0.0"}]},{"type":"text","value":" and run in production mode:"}]},{"type":"element","tag":"code","props":{"code":"// on Dokku Server\r\ndokku config:set my-nuxt-app HOST=0.0.0.0 NODE_ENV=production\n","language":"bash"},"children":[{"type":"element","tag":"pre","props":{},"children":[{"type":"element","tag":"code","props":{"__ignoreMap":""},"children":[{"type":"element","tag":"span","props":{"class":"line"},"children":[{"type":"element","tag":"span","props":{"class":"ct-eb4c6d"},"children":[{"type":"text","value":"// on Dokku Server"}]}]},{"type":"element","tag":"span","props":{"class":"line"},"children":[{"type":"element","tag":"span","props":{"class":"ct-eb4c6d"},"children":[{"type":"text","value":"dokku config:set my-nuxt-app HOST=0.0.0.0 NODE_ENV=production"}]}]}]}]}]},{"type":"element","tag":"p","props":{},"children":[{"type":"text","value":"You should see these 3 lines when you type "},{"type":"element","tag":"code-inline","props":{},"children":[{"type":"text","value":"dokku config my-nuxt-app"}]}]},{"type":"element","tag":"p","props":{},"children":[{"type":"element","tag":"img","props":{"alt":"nuxt config vars Dokku","src":"https://i.imgur.com/9FNsaoQ.png"},"children":[]}]},{"type":"element","tag":"p","props":{},"children":[{"type":"text","value":"Then, we tell Dokku to launch "},{"type":"element","tag":"code-inline","props":{},"children":[{"type":"text","value":"npm run build"}]},{"type":"text","value":" via the "},{"type":"element","tag":"code-inline","props":{},"children":[{"type":"text","value":"scripts.dokku.predeploy"}]},{"type":"text","value":" script in our project "},{"type":"element","tag":"code-inline","props":{},"children":[{"type":"text","value":"app.json"}]},{"type":"text","value":":"}]},{"type":"element","tag":"p","props":{},"children":[{"type":"element","tag":"code-inline","props":{},"children":[{"type":"text","value":"create a file name app.json in our project root folder"}]}]},{"type":"element","tag":"code","props":{"code":"{\r\n  \"scripts\": {\r\n    \"dokku\": {\r\n      \"predeploy\": \"npm run build\"\r\n    }\r\n  }\r\n}\n","language":"js"},"children":[{"type":"element","tag":"pre","props":{},"children":[{"type":"element","tag":"code","props":{"__ignoreMap":""},"children":[{"type":"element","tag":"span","props":{"class":"line"},"children":[{"type":"element","tag":"span","props":{"class":"ct-eb4c6d"},"children":[{"type":"text","value":"{"}]}]},{"type":"element","tag":"span","props":{"class":"line"},"children":[{"type":"element","tag":"span","props":{"class":"ct-30a321"},"children":[{"type":"text","value":"  "}]},{"type":"element","tag":"span","props":{"class":"ct-b240f2"},"children":[{"type":"text","value":"\""}]},{"type":"element","tag":"span","props":{"class":"ct-3e188f"},"children":[{"type":"text","value":"scripts"}]},{"type":"element","tag":"span","props":{"class":"ct-b240f2"},"children":[{"type":"text","value":"\""}]},{"type":"element","tag":"span","props":{"class":"ct-30a321"},"children":[{"type":"text","value":": {"}]}]},{"type":"element","tag":"span","props":{"class":"line"},"children":[{"type":"element","tag":"span","props":{"class":"ct-30a321"},"children":[{"type":"text","value":"    "}]},{"type":"element","tag":"span","props":{"class":"ct-b240f2"},"children":[{"type":"text","value":"\""}]},{"type":"element","tag":"span","props":{"class":"ct-3e188f"},"children":[{"type":"text","value":"dokku"}]},{"type":"element","tag":"span","props":{"class":"ct-b240f2"},"children":[{"type":"text","value":"\""}]},{"type":"element","tag":"span","props":{"class":"ct-f3f086"},"children":[{"type":"text","value":":"}]},{"type":"element","tag":"span","props":{"class":"ct-30a321"},"children":[{"type":"text","value":" {"}]}]},{"type":"element","tag":"span","props":{"class":"line"},"children":[{"type":"element","tag":"span","props":{"class":"ct-30a321"},"children":[{"type":"text","value":"      "}]},{"type":"element","tag":"span","props":{"class":"ct-b240f2"},"children":[{"type":"text","value":"\""}]},{"type":"element","tag":"span","props":{"class":"ct-3e188f"},"children":[{"type":"text","value":"predeploy"}]},{"type":"element","tag":"span","props":{"class":"ct-b240f2"},"children":[{"type":"text","value":"\""}]},{"type":"element","tag":"span","props":{"class":"ct-f3f086"},"children":[{"type":"text","value":":"}]},{"type":"element","tag":"span","props":{"class":"ct-30a321"},"children":[{"type":"text","value":" "}]},{"type":"element","tag":"span","props":{"class":"ct-b240f2"},"children":[{"type":"text","value":"\""}]},{"type":"element","tag":"span","props":{"class":"ct-3e188f"},"children":[{"type":"text","value":"npm run build"}]},{"type":"element","tag":"span","props":{"class":"ct-b240f2"},"children":[{"type":"text","value":"\""}]}]},{"type":"element","tag":"span","props":{"class":"line"},"children":[{"type":"element","tag":"span","props":{"class":"ct-eb4c6d"},"children":[{"type":"text","value":"    }"}]}]},{"type":"element","tag":"span","props":{"class":"line"},"children":[{"type":"element","tag":"span","props":{"class":"ct-eb4c6d"},"children":[{"type":"text","value":"  }"}]}]},{"type":"element","tag":"span","props":{"class":"line"},"children":[{"type":"element","tag":"span","props":{"class":"ct-eb4c6d"},"children":[{"type":"text","value":"}"}]}]}]}]}]},{"type":"element","tag":"p","props":{},"children":[{"type":"text","value":"To launch the application we run "},{"type":"element","tag":"code-inline","props":{},"children":[{"type":"text","value":"npm run start"}]},{"type":"text","value":" using the "},{"type":"element","tag":"a","props":{"href":"http://dokku.viewdocs.io/dokku/deployment/methods/dockerfiles/#procfiles-and-multiple-processes","rel":["nofollow"]},"children":[{"type":"text","value":"Procfile"}]},{"type":"text","value":":"}]},{"type":"element","tag":"code","props":{"code":"web: npm run start\n"},"children":[{"type":"element","tag":"pre","props":{},"children":[{"type":"element","tag":"code","props":{"__ignoreMap":""},"children":[{"type":"element","tag":"span","props":{"class":"line"},"children":[{"type":"element","tag":"span","props":{},"children":[{"type":"text","value":"web: npm run start"}]}]}]}]}]},{"type":"element","tag":"p","props":{},"children":[{"type":"text","value":"Finally, we can push our app on Dokku with:"}]},{"type":"element","tag":"code","props":{"code":"// commit your change before push.\r\ngit remote add dokku dokku@yourServer:my-nuxt-app\r\ngit push dokku master\n","language":"bash"},"children":[{"type":"element","tag":"pre","props":{},"children":[{"type":"element","tag":"code","props":{"__ignoreMap":""},"children":[{"type":"element","tag":"span","props":{"class":"line"},"children":[{"type":"element","tag":"span","props":{"class":"ct-eb4c6d"},"children":[{"type":"text","value":"// commit your change before push."}]}]},{"type":"element","tag":"span","props":{"class":"line"},"children":[{"type":"element","tag":"span","props":{"class":"ct-eb4c6d"},"children":[{"type":"text","value":"git remote add dokku dokku@yourServer:my-nuxt-app"}]}]},{"type":"element","tag":"span","props":{"class":"line"},"children":[{"type":"element","tag":"span","props":{"class":"ct-eb4c6d"},"children":[{"type":"text","value":"git push dokku master"}]}]}]}]}]},{"type":"element","tag":"p","props":{},"children":[{"type":"text","value":"Voilà! Our Nuxt application is now hosted on Dokku!"}]},{"type":"element","tag":"style","children":[{"type":"text","value":".ct-f3f086{color:#F286C4}.ct-3e188f{color:#E7EE98}.ct-b240f2{color:#DEE492}.ct-30a321{color:#F6F6F4}.ct-eb4c6d{color:#F6F6F4}.sepia .ct-eb4c6d{color:#F8F8F2}.dark .ct-eb4c6d{color:#C9D1D9}.dark .ct-30a321{color:#C9D1D9}.sepia .ct-30a321{color:#F8F8F2}.dark .ct-b240f2{color:#A5D6FF}.sepia .ct-b240f2{color:#E6DB74}.dark .ct-3e188f{color:#A5D6FF}.sepia .ct-3e188f{color:#E6DB74}.dark .ct-f3f086{color:#C9D1D9}.sepia .ct-f3f086{color:#F8F8F2}"}]}],"toc":{"title":"","searchDepth":2,"depth":2,"links":[]}},"_type":"markdown","_id":"content:deployments:folder2:dokku.md","_source":"content","_file":"deployments/folder2/dokku.md","_extension":"md"}